qtass/__init__.py
qtass/styles/material/LICENSE
qtass/styles/material/README.md
qtass/styles/material/fonts/roboto/LICENSE
qtass/styles/material/fonts/roboto/Roboto-Black.ttf
qtass/styles/material/fonts/roboto/Roboto-BlackItalic.ttf
qtass/styles/material/fonts/roboto/Roboto-Bold.ttf
qtass/styles/material/fonts/roboto/Roboto-BoldItalic.ttf
qtass/styles/material/fonts/roboto/Roboto-Italic.ttf
qtass/styles/material/fonts/roboto/Roboto-Light.ttf
qtass/styles/material/fonts/roboto/Roboto-LightItalic.ttf
qtass/styles/material/fonts/roboto/Roboto-Medium.ttf
qtass/styles/material/fonts/roboto/Roboto-MediumItalic.ttf
qtass/styles/material/fonts/roboto/Roboto-Regular.ttf
qtass/styles/material/fonts/roboto/Roboto-Thin.ttf
qtass/styles/material/fonts/roboto/Roboto-ThinItalic.ttf
qtass/styles/material/fonts/roboto/RobotoCondensed-Bold.ttf
qtass/styles/material/fonts/roboto/RobotoCondensed-BoldItalic.ttf
qtass/styles/material/fonts/roboto/RobotoCondensed-Italic.ttf
qtass/styles/material/fonts/roboto/RobotoCondensed-Light.ttf
qtass/styles/material/fonts/roboto/RobotoCondensed-LightItalic.ttf
qtass/styles/material/fonts/roboto/RobotoCondensed-Regular.ttf
qtass/styles/material/logo/logo.svg
qtass/styles/material/logo/logo_frame.svg
qtass/styles/material/material.css
qtass/styles/material/material.json
qtass/styles/material/material.nsh
qtass/styles/material/material_icon.svg
qtass/styles/material/resources/__init__.py
qtass/styles/material/resources/base.svg
qtass/styles/material/resources/branch-closed.svg
qtass/styles/material/resources/branch-end.svg
qtass/styles/material/resources/branch-more.svg
qtass/styles/material/resources/branch-open.svg
qtass/styles/material/resources/checkbox_checked.svg
qtass/styles/material/resources/checkbox_checked_invert.svg
qtass/styles/material/resources/checkbox_indeterminate.svg
qtass/styles/material/resources/checkbox_indeterminate_invert.svg
qtass/styles/material/resources/checkbox_unchecked.svg
qtass_pyside6-0.9.3.dist-info/METADATA
qtass_pyside6-0.9.3.dist-info/WHEEL
qtass_pyside6-0.9.3.dist-info/RECORD
