Metadata-Version: 2.3
Name: qtass-pyside6
Version: 0.9.3
Summary: Python version of Qt Advanced Styplesheets Library
Author: Uwe Kindler
Requires-Python: >=3.12,<3.14
Classifier: Development Status :: 4 - Beta
Classifier: Intended Audience :: Developers
Classifier: Operating System :: OS Independent
Classifier: Programming Language :: Python :: 3
Classifier: Programming Language :: Python :: 3.12
Classifier: Programming Language :: Python :: 3.13
Requires-Dist: jinja2 (>=3.1.6,<4.0.0)
Requires-Dist: pyside6 (>=6.9.0,<7.0.0)
Project-URL: Bug Tracker, https://gitlab.com/gitlabuser0xFFFF/nv200_python_lib/-/issues
Project-URL: Documentation, https://nv200-python-lib-e9158a.gitlab.io/
Project-URL: Homepage, https://gitlab.com/gitlabuser0xFFFF/nv200_python_lib
Project-URL: Source, https://gitlab.com/gitlabuser0xFFFF/nv200_python_lib
